data_completion_tool/__init__.py
data_completion_tool/dct.py
data_completion_tool/py.typed
data_completion_tool-0.3.2.dist-info/METADATA
data_completion_tool-0.3.2.dist-info/WHEEL
data_completion_tool-0.3.2.dist-info/licenses/LICENSE
data_completion_tool-0.3.2.dist-info/RECORD
