Metadata-Version: 2.4
Name: data-completion-tool
Version: 0.3.2
Summary: Automatic hierarchical dataset interpolation and disaggregation
Author-email: francois-verzier <francois.verzier@univ-grenoble-alpes.fr>
License-File: LICENSE
Classifier: Development Status :: 3 - Alpha
Classifier: Environment :: Console
Classifier: Intended Audience :: Science/Research
Classifier: License :: OSI Approved :: GNU Lesser General Public License v3 (LGPLv3)
Classifier: Operating System :: OS Independent
Classifier: Programming Language :: Python
Classifier: Programming Language :: Python :: 3.10
Classifier: Programming Language :: Python :: 3.11
Classifier: Programming Language :: Python :: 3.12
Classifier: Programming Language :: Python :: 3.13
Classifier: Programming Language :: Python :: 3.14
Classifier: Topic :: Scientific/Engineering
Requires-Python: <4.0,>=3.10
Requires-Dist: matplotlib>=3.10.8
Requires-Dist: openpyxl>=3.1.5
Requires-Dist: pandas>=2.3.3
